Metadata-Version: 1.0
Name: web-trawler
Version: 0.2.0
Summary: Trawl web pages for files to download
Home-page: https://gitlab.com/dlab-indecol/web_trawler
Author: Gorm Roedder
Author-email: gormroedder@gmail.com
License: GPLv3
Platform: UNKNOWN
